odoo/addons/fs_storage/README.rst
odoo/addons/fs_storage/__init__.py
odoo/addons/fs_storage/__manifest__.py
odoo/addons/fs_storage/odoo_file_system.py
odoo/addons/fs_storage/rooted_dir_file_system.py
odoo/addons/fs_storage/demo/fs_storage_demo.xml
odoo/addons/fs_storage/i18n/es.po
odoo/addons/fs_storage/i18n/fs_storage.pot
odoo/addons/fs_storage/i18n/it.po
odoo/addons/fs_storage/i18n/storage_backend.pot
odoo/addons/fs_storage/i18n/zh_CN.po
odoo/addons/fs_storage/models/__init__.py
odoo/addons/fs_storage/models/fs_storage.py
odoo/addons/fs_storage/models/ir_model.py
odoo/addons/fs_storage/models/ir_model_fields.py
odoo/addons/fs_storage/readme/CONTRIBUTORS.md
odoo/addons/fs_storage/readme/DESCRIPTION.md
odoo/addons/fs_storage/readme/HISTORY.md
odoo/addons/fs_storage/readme/ROADMAP.md
odoo/addons/fs_storage/readme/USAGE.md
odoo/addons/fs_storage/readme/newsfragments/.gitignore
odoo/addons/fs_storage/security/ir.model.access.csv
odoo/addons/fs_storage/static/description/icon.png
odoo/addons/fs_storage/static/description/index.html
odoo/addons/fs_storage/tests/__init__.py
odoo/addons/fs_storage/tests/common.py
odoo/addons/fs_storage/tests/test_fs_storage.py
odoo/addons/fs_storage/upgrades/18.0.2.1.0/post-update.py
odoo/addons/fs_storage/views/fs_storage_view.xml
odoo/addons/fs_storage/wizards/__init__.py
odoo/addons/fs_storage/wizards/fs_test_connection.py
odoo/addons/fs_storage/wizards/fs_test_connection.xml
odoo_addon_fs_storage-18.0.2.1.0.1.dist-info/METADATA
odoo_addon_fs_storage-18.0.2.1.0.1.dist-info/WHEEL
odoo_addon_fs_storage-18.0.2.1.0.1.dist-info/top_level.txt
odoo_addon_fs_storage-18.0.2.1.0.1.dist-info/RECORD
